[{"propertyFeeTotal":"324000","contractStartTime":"2016-09-10","rentTotal":"2131776","paymentType":"月付","period":"60 ","brandName":"飞行吧","rentType":"固定租金","storeNo":"S4a-1F-001a,S4a-2F-001a","rentFreePeriod":"3","floorNo":"1,2","deductPercent":"","contractEndTime":"2021-09-09","commercialType":"餐饮","contractId":"SYQBZZ15003","square":"216"},{"propertyFeeTotal":"381459.38","contractStartTime":"2016-09-10","rentTotal":"1941660","paymentType":"月付","period":"60 ","brandName":"小杨生煎","rentType":"固定租金","storeNo":"B1-79,B1-80","rentFreePeriod":"0","floorNo":"-1","deductPercent":"","contractEndTime":"2021-09-09","commercialType":"餐饮","contractId":"SYQBZZ15033","square":"96.6"},{"propertyFeeTotal":"62290.8","contractStartTime":"2016-09-10","rentTotal":"318067.20000000001","paymentType":"月付","period":"36 ","brandName":"快乐柠檬","rentType":"固定租金","storeNo":"B1-85","rentFreePeriod":"0","floorNo":"-1","deductPercent":"","contractEndTime":"2019-09-09","commercialType":"餐饮","contractId":"SYQBZZ15005","square":"26.4"},{"propertyFeeTotal":"205876.45","contractStartTime":"2016-09-10","rentTotal":"1059019.2","paymentType":"月付","period":"36 ","brandName":"麻辣8子（密辣）","rentType":"固定租金","storeNo":"B1-86,B1-87","rentFreePeriod":"0","floorNo":"-1","deductPercent":"","contractEndTime":"2019-09-09","commercialType":"餐饮","contractId":"SYQBZZ15009","square":"87.9"},{"propertyFeeTotal":"56942.6","contractStartTime":"2016-09-10","rentTotal":"291852","paymentType":"月付","period":"36 ","brandName":"茂棒","rentType":"固定租金","storeNo":"B1-90","rentFreePeriod":"0","floorNo":"-1","deductPercent":"","contractEndTime":"2019-09-09","commercialType":"餐饮","contractId":"SYQBZZ15007","square":"24.2"},{"propertyFeeTotal":"85452.35","contractStartTime":"2016-09-10","rentTotal":"490654.08","paymentType":"月付","period":"36 ","brandName":"卡西欧","rentType":"固定租金","storeNo":"S5-1F-005","rentFreePeriod":"0","floorNo":"1","deductPercent":"","contractEndTime":"2019-09-09","commercialType":"配套","contractId":"SYQBZZ16153","square":"36.119999999999997"},{"propertyFeeTotal":"66171.28","contractStartTime":"2016-09-10","rentTotal":"309132","paymentType":"月付","period":"36 ","brandName":"咔趣热狗","rentType":"固定租金","storeNo":"B1-97","rentFreePeriod":"0","floorNo":"-1","deductPercent":"","contractEndTime":"2019-09-09","commercialType":"餐饮","contractId":"SYQBZZ15016","square":"27.7"},{"propertyFeeTotal":"72908.55","contractStartTime":"2016-09-10","rentTotal":"327305.17","paymentType":"月付","period":"36 ","brandName":"利强记","rentType":"固定租金","storeNo":"B1-92","rentFreePeriod":"0","floorNo":"-1","deductPercent":"","contractEndTime":"2019-09-09","commercialType":"餐饮","contractId":"SYQBZZ15054","square":"30.9"},{"propertyFeeTotal":"730704","contractStartTime":"2016-09-10","rentTotal":"2657368.0099999998","paymentType":"月付","period":"60 ","brandName":"正殿老张牛肉面","rentType":"固定租金","storeNo":"S3-1F-001d,S3-2F-001a","rentFreePeriod":"2","floorNo":"1,2","deductPercent":"","contractEndTime":"2021-09-09","commercialType":"餐饮","contractId":"SYQBZZ15058","square":"187.36"},{"propertyFeeTotal":"196560","contractStartTime":"2016-09-10","rentTotal":"665448","paymentType":"月付","period":"36 ","brandName":"金大福","rentType":"固定租金","storeNo":"B1-8,B1-10","rentFreePeriod":"2","floorNo":"-1","deductPercent":"","contractEndTime":"2019-09-09","commercialType":"配套","contractId":"SYQBZZ15051","square":"84"},{"propertyFeeTotal":"1602666","contractStartTime":"2016-09-10","rentTotal":"3311696.97","paymentType":"月付","period":"60 ","brandName":"咕噜咕噜","rentType":"固定租金","storeNo":"S4a-3F-005a","rentFreePeriod":"3","floorNo":"3","deductPercent":"","contractEndTime":"2021-09-09","commercialType":"儿童","contractId":"SYQBZZ15053","square":"410.94"},{"propertyFeeTotal":"0","contractStartTime":"2016-09-10","rentTotal":"0","paymentType":"季付","period":"240 ","brandName":"H&M","rentType":"提成租金","storeNo":"S2-1F-008/001a/001c/002c/007a-3/001b-2+S2-2F-006/001a/001b-2/002a-2/002b-2","rentFreePeriod":"0","floorNo":"1","deductPercent":"5.5%","contractEndTime":"2036-09-09","commercialType":"服装","contractId":"SYQBZZ15055","square":"2100"},{"propertyFeeTotal":"160438.42000000001","contractStartTime":"2016-09-10","rentTotal":"687192","paymentType":"月付","period":"36 ","brandName":"太麻里台湾私房牛肉面","rentType":"固定租金","storeNo":"B1-103,B1-105","rentFreePeriod":"0","floorNo":"-1","deductPercent":"","contractEndTime":"2019-09-09","commercialType":"餐饮","contractId":"SYQBZZ15060","square":"68.5"},{"propertyFeeTotal":"2032386.4","contractStartTime":"2016-09-10","rentTotal":"6061194","paymentType":"月付","period":"96 ","brandName":"南京大排档","rentType":"固定租金","storeNo":"S4b-4F-001a","rentFreePeriod":"8","floorNo":"4","deductPercent":"","contractEndTime":"2024-09-09","commercialType":"餐饮","contractId":"SYQBZZ15064","square":"705.2"},{"propertyFeeTotal":"504483.2","contractStartTime":"2016-09-10","rentTotal":"1660313.6000000001","paymentType":"月付","period":"36 ","brandName":"港轩","rentType":"固定租金","storeNo":"B1-75,B1-76,B1-165,B1-166,B1-167,B1-168","rentFreePeriod":"2","floorNo":"-1","deductPercent":"","contractEndTime":"2019-09-09","commercialType":"餐饮","contractId":"SYQBZZ15065","square":"214.4"},{"propertyFeeTotal":"165819.32999999999","contractStartTime":"2016-09-10","rentTotal":"750480","paymentType":"月付","period":"24 ","brandName":"雪冰","rentType":"固定租金","storeNo":"B1-186-188,B1-189-191","rentFreePeriod":"0","floorNo":"-1","deductPercent":"","contractEndTime":"2018-09-09","commercialType":"餐饮","contractId":"SYQBZZ15074","square":"106"},{"propertyFeeTotal":"36440.57","contractStartTime":"2016-09-10","rentTotal":"132049.5","paymentType":"月付","period":"24 ","brandName":"七彩鲜果屋","rentType":"固定租金","storeNo":"S1-4F-002","rentFreePeriod":"2","floorNo":"4","deductPercent":"","contractEndTime":"2018-09-09","commercialType":"餐饮","contractId":"SYQBZZ15070","square":"22.65"},{"propertyFeeTotal":"3569972.4","contractStartTime":"2016-09-02","rentTotal":"150000","paymentType":"季付","period":"180 ","brandName":"百老汇","rentType":"两者取高","storeNo":"S1-4F-006,S1-4F-005b","rentFreePeriod":"0","floorNo":"4,5","deductPercent":"","contractEndTime":"2031-09-01","commercialType":"影院","contractId":"SYQBZZ15077","square":"3305.53"},{"propertyFeeTotal":"40720.120000000003","contractStartTime":"2016-09-10","rentTotal":"192381.31","paymentType":"月付","period":"24 ","brandName":"YONEX等","rentType":"固定租金","storeNo":"S5-2F-003","rentFreePeriod":"1","floorNo":"2","deductPercent":"","contractEndTime":"2018-09-09","commercialType":"配套","contractId":"SYQBZZ16003","square":"25.31"},{"propertyFeeTotal":"354267.17","contractStartTime":"2016-09-10","rentTotal":"950306.4","paymentType":"月付","period":"36 ","brandName":"ABS","rentType":"固定租金","storeNo":"B1-55,B1-57,B1-58","rentFreePeriod":"0","floorNo":"-1","deductPercent":"","contractEndTime":"2019-09-09","commercialType":"配套","contractId":"SYQBZZ16008","square":"148.30000000000001"},{"propertyFeeTotal":"35073.040000000001","contractStartTime":"2016-09-10","rentTotal":"170723.07","paymentType":"月付","period":"24 ","brandName":"金煜珠宝","rentType":"固定租金","storeNo":"B1-230,B1-231","rentFreePeriod":"1","floorNo":"-1","deductPercent":"","contractEndTime":"2018-09-09","commercialType":"配套","contractId":"SYQBZZ16004","square":"21.8"},{"propertyFeeTotal":"219960","contractStartTime":"2016-09-10","rentTotal":"825649","paymentType":"月付","period":"36 ","brandName":"周大生","rentType":"固定租金","storeNo":"B1-4,B1-6","rentFreePeriod":"3","floorNo":"-1","deductPercent":"","contractEndTime":"2019-09-09","commercialType":"配套","contractId":"SYQBZZ16011","square":"94"},{"propertyFeeTotal":"1603945.86","contractStartTime":"2016-09-10","rentTotal":"4834151.2699999996","paymentType":"月付","period":"60 ","brandName":"爱尚英语","rentType":"固定租金","storeNo":"S3-3F-003a,S3-3F-003b","rentFreePeriod":"3","floorNo":"3","deductPercent":"","contractEndTime":"2021-09-09","commercialType":"儿童","contractId":"SYQBZZ16009","square":"406.18"},{"propertyFeeTotal":"70980","contractStartTime":"2016-09-10","rentTotal":"255420","paymentType":"月付","period":"24 ","brandName":"棉购","rentType":"固定租金","storeNo":"B1-209","rentFreePeriod":"2","floorNo":"-1","deductPercent":"","contractEndTime":"2018-09-09","commercialType":"配套","contractId":"SYQBZZ16013","square":"45"},{"propertyFeeTotal":"13518.63","contractStartTime":"2016-09-10","rentTotal":"70459.199999999997","paymentType":"月付","period":"12 ","brandName":"乐堂私房茶","rentType":"固定租金","storeNo":"S1-1F-018","rentFreePeriod":"0","floorNo":"1","deductPercent":"","contractEndTime":"2017-09-09","commercialType":"餐饮","contractId":"SYQBZZ16040","square":"16.309999999999999"},{"propertyFeeTotal":"92042.58","contractStartTime":"2016-09-10","rentTotal":"503972.39","paymentType":"月付","period":"36 ","brandName":"爱学习","rentType":"固定租金","storeNo":"S4a-3F-001","rentFreePeriod":"0","floorNo":"3","deductPercent":"","contractEndTime":"2019-09-09","commercialType":"配套","contractId":"SYQBZZ15001","square":"38.53"},{"propertyFeeTotal":"54976.35","contractStartTime":"2016-09-10","rentTotal":"280438.8","paymentType":"月付","period":"36 ","brandName":"丸来玩趣","rentType":"固定租金","storeNo":"B1-88","rentFreePeriod":"0","floorNo":"-1","deductPercent":"","contractEndTime":"2019-09-09","commercialType":"餐饮","contractId":"SYQBZZ15010","square":"23.3"},{"propertyFeeTotal":"492424.88","contractStartTime":"2016-09-10","rentTotal":"3582234.55","paymentType":"月付","period":"60 ","brandName":"塔哈尔","rentType":"固定租金","storeNo":"T1-72,T1-74,T1-76","rentFreePeriod":"3","floorNo":"1","deductPercent":"","contractEndTime":"2021-09-09","commercialType":"餐饮","contractId":"SYQBZZ15043","square":"326.64999999999998"},{"propertyFeeTotal":"766077","contractStartTime":"2016-09-10","rentTotal":"2324159.77","paymentType":"月付","period":"60 ","brandName":"新石器烤肉","rentType":"固定租金","storeNo":"S3-4F-001b","rentFreePeriod":"0","floorNo":"4","deductPercent":"","contractEndTime":"2021-09-09","commercialType":"餐饮","contractId":"SYQBZZ15044","square":"196.43"},{"propertyFeeTotal":"517257","contractStartTime":"2016-09-10","rentTotal":"1873266.13","paymentType":"月付","period":"60 ","brandName":"安东鸡","rentType":"固定租金","storeNo":"S2-4F-003","rentFreePeriod":"0","floorNo":"4","deductPercent":"","contractEndTime":"2021-09-09","commercialType":"餐饮","contractId":"SYQBZZ15013","square":"132.63"},{"propertyFeeTotal":"3559742.08","contractStartTime":"2016-09-10","rentTotal":"19553505","paymentType":"季付","period":"72 ","brandName":"爱食馆美食广场","rentType":"固定租金","storeNo":"B1-94/96/98/100/102/104/106/108/110-113/115-163","rentFreePeriod":"5","floorNo":"-1","deductPercent":"","contractEndTime":"2022-09-09","commercialType":"餐饮","contractId":"SYQBZZ15017","square":"2234"},{"propertyFeeTotal":"62244","contractStartTime":"2016-09-10","rentTotal":"287280","paymentType":"月付","period":"36 ","brandName":"绝味鸭脖","rentType":"固定租金","storeNo":"B1-164","rentFreePeriod":"0","floorNo":"-1","deductPercent":"","contractEndTime":"2019-09-09","commercialType":"餐饮","contractId":"SYQBZZ15019","square":"26.6"},{"propertyFeeTotal":"334725.3","contractStartTime":"2016-09-10","rentTotal":"1334289.6000000001","paymentType":"月付","period":"60 ","brandName":"酒窝甜品","rentType":"固定租金","storeNo":"B1-101,B1-99","rentFreePeriod":"0","floorNo":"-1","deductPercent":"","contractEndTime":"2021-09-09","commercialType":"餐饮","contractId":"SYQBZZ15031","square":"85.4"},{"propertyFeeTotal":"99307.87","contractStartTime":"2016-09-10","rentTotal":"457920","paymentType":"月付","period":"36 ","brandName":"天香豆蔻","rentType":"固定租金","storeNo":"B1-89","rentFreePeriod":"0","floorNo":"-1","deductPercent":"","contractEndTime":"2019-09-09","commercialType":"餐饮","contractId":"SYQBZZ15037","square":"42.4"},{"propertyFeeTotal":"6043496.7400000002","contractStartTime":"2016-09-10","rentTotal":"18061592.600000001","paymentType":"季付","period":"96 ","brandName":"威尔士健身","rentType":"固定租金","storeNo":"S5-3F-001/002/006","rentFreePeriod":"3","floorNo":"3","deductPercent":"","contractEndTime":"2024-09-09","commercialType":"配套","contractId":"SYQBZZ15038","square":"2089.1"},{"propertyFeeTotal":"73109.399999999994","contractStartTime":"2016-09-10","rentTotal":"286416","paymentType":"月付","period":"24 ","brandName":"六六顺","rentType":"固定租金","storeNo":"B1-194,B1-195","rentFreePeriod":"0","floorNo":"-1","deductPercent":"","contractEndTime":"2018-09-09","commercialType":"配套","contractId":"SYQBZZ15050","square":"46.8"},{"propertyFeeTotal":"38802.400000000001","contractStartTime":"2016-09-10","rentTotal":"159408","paymentType":"月付","period":"24 ","brandName":"杜茜","rentType":"固定租金","storeNo":"B1-91","rentFreePeriod":"0","floorNo":"-1","deductPercent":"","contractEndTime":"2018-09-09","commercialType":"餐饮","contractId":"SYQBZZ15052","square":"24.6"},{"propertyFeeTotal":"1836744","contractStartTime":"2016-09-10","rentTotal":"5394454.3300000001","paymentType":"月付","period":"60 ","brandName":"乐乐派","rentType":"固定租金","storeNo":"S3-3F-001a/001b","rentFreePeriod":"1","floorNo":"3","deductPercent":"","contractEndTime":"2021-09-09","commercialType":"儿童","contractId":"SYQBZZ15061","square":"470.96"},{"propertyFeeTotal":"577174.87","contractStartTime":"2016-09-10","rentTotal":"2128502.4","paymentType":"月付","period":"36 ","brandName":"名创优品","rentType":"固定租金","storeNo":"B1-34,B1-36,B1-38,B1-40,B1-221,B1-222,B1-224,B1-225","rentFreePeriod":"3","floorNo":"-1","deductPercent":"","contractEndTime":"2019-09-09","commercialType":"配套","contractId":"SYQBZZ15059","square":"246.2"},{"propertyFeeTotal":"78000","contractStartTime":"2016-09-10","rentTotal":"302500","paymentType":"月付","period":"24 ","brandName":"果餐","rentType":"固定租金","storeNo":"B1-64","rentFreePeriod":"2","floorNo":"-1","deductPercent":"","contractEndTime":"2018-09-09","commercialType":"餐饮","contractId":"SYQBZZ15071","square":"50"},{"propertyFeeTotal":"313794","contractStartTime":"2016-09-10","rentTotal":"1232379","paymentType":"月付","period":"36 ","brandName":"中国黄金","rentType":"固定租金","storeNo":"B1-3/5-R","rentFreePeriod":"2","floorNo":"-1","deductPercent":"","contractEndTime":"2019-09-09","commercialType":"配套","contractId":"SYQBZZ15072","square":"134.1"},{"propertyFeeTotal":"135784.13","contractStartTime":"2016-09-10","rentTotal":"615412","paymentType":"月付","period":"24 ","brandName":"阿秦家味","rentType":"固定租金","storeNo":"B1-175-178,B1-179-182","rentFreePeriod":"1","floorNo":"-1","deductPercent":"","contractEndTime":"2018-09-09","commercialType":"餐饮","contractId":"SYQBZZ16005","square":"86.8"},{"propertyFeeTotal":"236340","contractStartTime":"2016-09-10","rentTotal":"1065634.17","paymentType":"月付","period":"36 ","brandName":"老鳯祥黄金","rentType":"固定租金","storeNo":"B1-16,B1-18","rentFreePeriod":"1","floorNo":"-1","deductPercent":"","contractEndTime":"2019-09-09","commercialType":"配套","contractId":"SYQBZZ16043","square":"101"},{"propertyFeeTotal":"53092.21","contractStartTime":"2016-09-10","rentTotal":"233640","paymentType":"月付","period":"24 ","brandName":"因草烟草","rentType":"固定租金","storeNo":"B1-193","rentFreePeriod":"0","floorNo":"-1","deductPercent":"","contractEndTime":"2018-09-09","commercialType":"配套","contractId":"SYQBZZ16031","square":"33"},{"propertyFeeTotal":"2995429.94","contractStartTime":"2016-09-10","rentTotal":"7278008","paymentType":"季付","period":"96 ","brandName":"汤姆熊","rentType":"固定租金","storeNo":"S1-3F-006b-1/006a-2","rentFreePeriod":"3","floorNo":"3","deductPercent":"","contractEndTime":"2024-09-09","commercialType":"配套","contractId":"SYQBZZ16015","square":"1032"},{"propertyFeeTotal":"48067.87","contractStartTime":"2016-09-10","rentTotal":"183562.54","paymentType":"月付","period":"24 ","brandName":"如意馄饨","rentType":"固定租金","storeNo":"B1-196","rentFreePeriod":"1","floorNo":"-1","deductPercent":"","contractEndTime":"2018-09-09","commercialType":"配套","contractId":"SYQBZZ16017","square":"30.77"},{"propertyFeeTotal":"101287.45","contractStartTime":"2016-09-10","rentTotal":"331030.93","paymentType":"月付","period":"36 ","brandName":"卡洛驰","rentType":"固定租金","storeNo":"S4a-2F-006-1","rentFreePeriod":"3","floorNo":"2","deductPercent":"","contractEndTime":"2019-09-09","commercialType":"配套","contractId":"SYQBZZ16022","square":"42.4"},{"propertyFeeTotal":"80964","contractStartTime":"2016-09-10","rentTotal":"388514.75","paymentType":"月付","period":"24 ","brandName":"万合至配","rentType":"固定租金","storeNo":"B1-27,B1-28","rentFreePeriod":"1","floorNo":"-1","deductPercent":"","contractEndTime":"2018-09-09","commercialType":"配套","contractId":"SYQBZZ16025","square":"51.9"},{"propertyFeeTotal":"2850431.33","contractStartTime":"2016-09-10","rentTotal":"16018693.470000001","paymentType":"月付","period":"96 ","brandName":"巴国布衣","rentType":"固定租金","storeNo":"H4a-1F-001/002/003,H4a-2F-001/002,H4a-3F-001","rentFreePeriod":"4","floorNo":"1,2,3","deductPercent":"","contractEndTime":"2024-09-09","commercialType":"餐饮","contractId":"SYQBZZ16024","square":"1184.8"},{"propertyFeeTotal":"191880","contractStartTime":"2016-09-10","rentTotal":"1019820.33","paymentType":"月付","period":"36 ","brandName":"天宝龙凤","rentType":"固定租金","storeNo":"B1-12,B1-14","rentFreePeriod":"1","floorNo":"-1","deductPercent":"","contractEndTime":"2019-09-09","commercialType":"配套","contractId":"SYQBZZ16026","square":"82"},{"propertyFeeTotal":"99266.34","contractStartTime":"2016-09-10","rentTotal":"481260","paymentType":"月付","period":"24 ","brandName":"优蜜","rentType":"固定租金","storeNo":"B1-171-174,B1-184,B1-185","rentFreePeriod":"0","floorNo":"-1","deductPercent":"","contractEndTime":"2018-09-09","commercialType":"餐饮","contractId":"SYQBZZ16032","square":"61.7"},{"propertyFeeTotal":"867750","contractStartTime":"2016-09-10","rentTotal":"2568540","paymentType":"月付","period":"60 ","brandName":"萨莉亚意式餐厅","rentType":"固定租金","storeNo":"B1-19","rentFreePeriod":"0","floorNo":"-1","deductPercent":"","contractEndTime":"2021-09-09","commercialType":"餐饮","contractId":"SYQBZZ16036","square":"222.5"},{"propertyFeeTotal":"209196","contractStartTime":"2016-09-10","rentTotal":"772416","paymentType":"月付","period":"24 ","brandName":"城隍庙金福银楼","rentType":"固定租金","storeNo":"B1-11/13-R","rentFreePeriod":"0","floorNo":"-1","deductPercent":"","contractEndTime":"2018-09-09","commercialType":"配套","contractId":"SYQBZZ16034","square":"134.1"},{"propertyFeeTotal":"137817.76999999999","contractStartTime":"2016-09-10","rentTotal":"482083.2","paymentType":"月付","period":"24 ","brandName":"足装秀","rentType":"固定租金","storeNo":"B1-227,B1-228,B1-30,B1-32","rentFreePeriod":"0","floorNo":"-1","deductPercent":"","contractEndTime":"2018-09-09","commercialType":"配套","contractId":"SYQBZZ16037","square":"88.1"},{"propertyFeeTotal":"215842.47","contractStartTime":"2016-09-10","rentTotal":"660669.1","paymentType":"月付","period":"36 ","brandName":"艾美家","rentType":"固定租金","storeNo":"B1-46,B1-48","rentFreePeriod":"3","floorNo":"-1","deductPercent":"","contractEndTime":"2019-09-09","commercialType":"配套","contractId":"SYQBZZ16038","square":"91.9"},{"propertyFeeTotal":"516015","contractStartTime":"2016-09-10","rentTotal":"3124986.84","paymentType":"月付","period":"60 ","brandName":"Uteam足球主题餐厅","rentType":"固定租金","storeNo":"S4a-1F-002,S4a-2F-002a/002b","rentFreePeriod":"0","floorNo":"1,2","deductPercent":"","contractEndTime":"2021-09-09","commercialType":"餐饮","contractId":"SYQBZZ16039","square":"344.01"},{"propertyFeeTotal":"264255.12","contractStartTime":"2016-09-10","rentTotal":"1062984.45","paymentType":"月付","period":"36 ","brandName":"孩之宝","rentType":"固定租金","storeNo":"S4b-3F-002b","rentFreePeriod":"3","floorNo":"3","deductPercent":"","contractEndTime":"2019-09-09","commercialType":"儿童","contractId":"SYQBZZ16041","square":"110.62"},{"propertyFeeTotal":"102889.45","contractStartTime":"2016-09-10","rentTotal":"927710.4","paymentType":"月付","period":"36 ","brandName":"大夹子先生","rentType":"固定租金","storeNo":"T1-68,T1-70","rentFreePeriod":"0","floorNo":"1","deductPercent":"","contractEndTime":"2019-09-09","commercialType":"餐饮","contractId":"SYQBZZ16061","square":"113.69"},{"propertyFeeTotal":"199234.91","contractStartTime":"2016-09-10","rentTotal":"2347072.5499999998","paymentType":"月付","period":"60 ","brandName":"五芳斋","rentType":"固定租金","storeNo":"T3-401,T3-403","rentFreePeriod":"0","floorNo":"1","deductPercent":"","contractEndTime":"2021-09-09","commercialType":"餐饮","contractId":"SYQBZZ16046","square":"131.18"},{"propertyFeeTotal":"23556","contractStartTime":"2016-09-10","rentTotal":"157644","paymentType":"月付","period":"12 ","brandName":"gotchurros","rentType":"固定租金","storeNo":"S1-1F-008","rentFreePeriod":"0","floorNo":"1","deductPercent":"","contractEndTime":"2017-09-09","commercialType":"餐饮","contractId":"SYQBZZ16059","square":"30.2"},{"propertyFeeTotal":"50340.53","contractStartTime":"2016-09-10","rentTotal":"480133.9","paymentType":"月付","period":"36 ","brandName":"赛百味","rentType":"固定租金","storeNo":"T4-7","rentFreePeriod":"1","floorNo":"1","deductPercent":"","contractEndTime":"2019-09-09","commercialType":"餐饮","contractId":"SYQBZZ16058","square":"54.79"},{"propertyFeeTotal":"461040","contractStartTime":"2016-09-10","rentTotal":"3038580","paymentType":"月付","period":"60 ","brandName":"zoo coffee","rentType":"固定租金","storeNo":"T5-1F-001-1","rentFreePeriod":"2","floorNo":"1","deductPercent":"","contractEndTime":"2021-09-09","commercialType":"餐饮","contractId":"SYQBZZ16060","square":"306"},{"propertyFeeTotal":"230273.17","contractStartTime":"2016-09-10","rentTotal":"1732842.72","paymentType":"月付","period":"36 ","brandName":"AMANI造型","rentType":"固定租金","storeNo":"T4-11,T4-373,T4-375","rentFreePeriod":"0","floorNo":"1","deductPercent":"","contractEndTime":"2019-09-09","commercialType":"配套","contractId":"SYQBZZ16056","square":"254.68"},{"propertyFeeTotal":"346138.65","contractStartTime":"2016-09-10","rentTotal":"1741769.1","paymentType":"月付","period":"36 ","brandName":"大益茶庭","rentType":"固定租金","storeNo":"S2-1F-006a,S2-1F-007b","rentFreePeriod":"1","floorNo":"1","deductPercent":"","contractEndTime":"2019-09-09","commercialType":"餐饮","contractId":"SYQBZZ16055","square":"146.69999999999999"},{"propertyFeeTotal":"444291.7","contractStartTime":"2016-09-10","rentTotal":"2084623.52","paymentType":"月付","period":"60 ","brandName":"岳豪酒庄","rentType":"固定租金","storeNo":"T5-1F-001-3/002,T5-2F-001c/001a-2/001b-2","rentFreePeriod":"3","floorNo":"1,2","deductPercent":"","contractEndTime":"2021-09-09","commercialType":"餐饮","contractId":"SYQBZZ16053","square":"296.02999999999997"},{"propertyFeeTotal":"256949.55","contractStartTime":"2016-09-10","rentTotal":"542322","paymentType":"月付","period":"36 ","brandName":"下雪的村庄","rentType":"固定租金","storeNo":"S1-1F-006","rentFreePeriod":"0","floorNo":"1","deductPercent":"","contractEndTime":"2019-09-09","commercialType":"餐饮","contractId":"SYQBZZ16052","square":"108.9"},{"propertyFeeTotal":"822588","contractStartTime":"2016-09-10","rentTotal":"1926121.44","paymentType":"月付","period":"60 ","brandName":"阿玛尼","rentType":"固定租金","storeNo":"S4a-3F-002-1","rentFreePeriod":"0","floorNo":"3","deductPercent":"","contractEndTime":"2021-09-09","commercialType":"配套","contractId":"SYQBZZ16066","square":"210.92"},{"propertyFeeTotal":"1347840","contractStartTime":"2016-09-10","rentTotal":"3179520","paymentType":"月付","period":"60 ","brandName":"丽江印象斑鱼府","rentType":"固定租金","storeNo":"S1-1F-003/004,S1-1F-005","rentFreePeriod":"2","floorNo":"1","deductPercent":"","contractEndTime":"2021-09-09","commercialType":"餐饮","contractId":"SYQBZZ16065","square":"345.6"},{"propertyFeeTotal":"25272","contractStartTime":"2016-09-10","rentTotal":"155520","paymentType":"月付","period":"24 ","brandName":"Zippo","rentType":"固定租金","storeNo":"S3-2F-003","rentFreePeriod":"0","floorNo":"2","deductPercent":"","contractEndTime":"2018-09-09","commercialType":"配套","contractId":"SYQBZZ16068","square":"16.2"},{"propertyFeeTotal":"616620","contractStartTime":"2016-09-10","rentTotal":"2931822.56","paymentType":"月付","period":"60 ","brandName":"培正逗点","rentType":"固定租金","storeNo":"T5-1F-001-2,T5-2F-001a-1/001b-1","rentFreePeriod":"3","floorNo":"1,2","deductPercent":"","contractEndTime":"2021-09-09","commercialType":"儿童","contractId":"SYQBZZ16069","square":"411.08"},{"propertyFeeTotal":"45365.67","contractStartTime":"2016-09-10","rentTotal":"150292.5","paymentType":"月付","period":"24 ","brandName":"桂源铺","rentType":"固定租金","storeNo":"B1-197","rentFreePeriod":"1","floorNo":"-1","deductPercent":"","contractEndTime":"2018-09-09","commercialType":"餐饮","contractId":"SYQBZZ16103","square":"29"},{"propertyFeeTotal":"39221.65","contractStartTime":"2016-09-10","rentTotal":"157720.75","paymentType":"月付","period":"24 ","brandName":"扬屋","rentType":"固定租金","storeNo":"B1-95","rentFreePeriod":"1","floorNo":"-1","deductPercent":"","contractEndTime":"2018-09-09","commercialType":"餐饮","contractId":"SYQBZZ16102","square":"24.9"},{"propertyFeeTotal":"45364.800000000003","contractStartTime":"2016-09-10","rentTotal":"165840","paymentType":"月付","period":"24 ","brandName":"秦友会","rentType":"固定租金","storeNo":"B1-183","rentFreePeriod":"1","floorNo":"-1","deductPercent":"","contractEndTime":"2018-09-09","commercialType":"餐饮","contractId":"SYQBZZ16104","square":"28.8"},{"propertyFeeTotal":"20806.080000000002","contractStartTime":"2016-09-10","rentTotal":"106080","paymentType":"月付","period":"24 ","brandName":"名表维修","rentType":"固定租金","storeNo":"B1-229","rentFreePeriod":"0","floorNo":"-1","deductPercent":"","contractEndTime":"2018-09-09","commercialType":"配套","contractId":"SYQBZZ16105","square":"13"},{"propertyFeeTotal":"722640.44","contractStartTime":"2016-09-10","rentTotal":"1746735","paymentType":"季付","period":"60 ","brandName":"ONLY","rentType":"两者取高","storeNo":"S4a-2F-007a/007b-1","rentFreePeriod":"6","floorNo":"2","deductPercent":"","contractEndTime":"2021-09-09","commercialType":"服装","contractId":"SYQBZZ16107","square":"183"},{"propertyFeeTotal":"48603.51","contractStartTime":"2016-09-10","rentTotal":"232617","paymentType":"月付","period":"24 ","brandName":"蘭芳园","rentType":"固定租金","storeNo":"S2-1F-006b-1","rentFreePeriod":"2","floorNo":"1","deductPercent":"","contractEndTime":"2018-09-09","commercialType":"餐饮","contractId":"SYQBZZ16108","square":"30.21"},{"propertyFeeTotal":"787365.15","contractStartTime":"2016-09-10","rentTotal":"1374844","paymentType":"月付","period":"36 ","brandName":"味三亭","rentType":"固定租金","storeNo":"S1-1F-002,S1-2F-001","rentFreePeriod":"3","floorNo":"1,2","deductPercent":"","contractEndTime":"2019-09-09","commercialType":"餐饮","contractId":"SYQBZZ16109","square":"333.7"},{"propertyFeeTotal":"76610.22","contractStartTime":"2016-09-10","rentTotal":"361032.96000000002","paymentType":"月付","period":"24 ","brandName":"青沐美睫","rentType":"固定租金","storeNo":"S1-4F-008","rentFreePeriod":"2","floorNo":"4","deductPercent":"","contractEndTime":"2018-09-09","commercialType":"配套","contractId":"SYQBZZ16110","square":"47.68"},{"propertyFeeTotal":"179618","contractStartTime":"2016-09-10","rentTotal":"883708.07","paymentType":"月付","period":"36 ","brandName":"豆花开了","rentType":"固定租金","storeNo":"S2-1F-009","rentFreePeriod":"1","floorNo":"1","deductPercent":"","contractEndTime":"2019-09-09","commercialType":"餐饮","contractId":"SYQBZZ16111","square":"75.19"},{"propertyFeeTotal":"724851.79","contractStartTime":"2016-09-10","rentTotal":"1752080.2","paymentType":"季付","period":"60 ","brandName":"杰克琼斯","rentType":"两者取高","storeNo":"S4a-2F-006-2/007b-2","rentFreePeriod":"6","floorNo":"2","deductPercent":"","contractEndTime":"2021-09-09","commercialType":"服装","contractId":"SYQBZZ16106","square":"183.56"},{"propertyFeeTotal":"69778.45","contractStartTime":"2016-09-10","rentTotal":"614812.07999999996","paymentType":"月付","period":"36 ","brandName":"爱茜茜里","rentType":"固定租金","storeNo":"S1-1F-016","rentFreePeriod":"0","floorNo":"1","deductPercent":"","contractEndTime":"2019-09-09","commercialType":"餐饮","contractId":"SYQBZZ16138","square":"29.21"},{"propertyFeeTotal":"666045","contractStartTime":"2016-09-10","rentTotal":"3149075.56","paymentType":"月付","period":"60 ","brandName":"雲鮨日料","rentType":"固定租金","storeNo":"S4a-1F-003a,S4a-2F-003","rentFreePeriod":"4","floorNo":"1,2","deductPercent":"","contractEndTime":"2021-09-09","commercialType":"餐饮","contractId":"SYQBZZ16122","square":"444.03"},{"propertyFeeTotal":"248440.9","contractStartTime":"2016-09-10","rentTotal":"763776","paymentType":"月付","period":"36 ","brandName":"大鼓米线","rentType":"固定租金","storeNo":"B1-107,B1-109","rentFreePeriod":"2","floorNo":"-1","deductPercent":"","contractEndTime":"2019-09-09","commercialType":"餐饮","contractId":"SYQBZZ16115","square":"104"},{"propertyFeeTotal":"178354.8","contractStartTime":"2016-09-10","rentTotal":"590552.56000000006","paymentType":"月付","period":"36 ","brandName":"有侬有意","rentType":"固定租金","storeNo":"S1-4F-001","rentFreePeriod":"2","floorNo":"5","deductPercent":"","contractEndTime":"2019-09-09","commercialType":"餐饮","contractId":"SYQBZZ16116","square":"76.22"},{"propertyFeeTotal":"46930","contractStartTime":"2016-09-10","rentTotal":"155475","paymentType":"月付","period":"24 ","brandName":"品食佳","rentType":"固定租金","storeNo":"B1-198","rentFreePeriod":"1","floorNo":"-1","deductPercent":"","contractEndTime":"2018-09-09","commercialType":"餐饮","contractId":"SYQBZZ16114","square":"30"},{"propertyFeeTotal":"925366.05","contractStartTime":"2016-09-10","rentTotal":"2028805.6","paymentType":"季付","period":"60 ","brandName":"晨光生活馆","rentType":"两者取高","storeNo":"B1-37,B1-39,B1-41,B1-43,B1-45,B1-47","rentFreePeriod":"5","floorNo":"-1","deductPercent":"","contractEndTime":"2021-09-09","commercialType":"配套","contractId":"SYQBZZ16199","square":"237.01"},{"propertyFeeTotal":"1707030","contractStartTime":"2016-09-10","rentTotal":"4749263.8499999996","paymentType":"季付","period":"60 ","brandName":"lesairs生活馆","rentType":"两者取高","storeNo":"B1-21,B1-22,B1-23,B1-24,B1-25,B1-26,B1-29,B1-31,B1-33,B1-35","rentFreePeriod":"3","floorNo":"-1","deductPercent":"","contractEndTime":"2021-09-09","commercialType":"配套","contractId":"SYQBZZ16120","square":"437.7"},{"propertyFeeTotal":"639405","contractStartTime":"2016-09-10","rentTotal":"3541706.92","paymentType":"月付","period":"60 ","brandName":"BOBO宠物空间","rentType":"固定租金","storeNo":"T2-28,T2-30,T2-32,T2-34,T2-36,T2-38,T2-40,T2-439","rentFreePeriod":"4","floorNo":"1","deductPercent":"","contractEndTime":"2021-09-09","commercialType":"配套","contractId":"SYQBZZ16128","square":"426.27"},{"propertyFeeTotal":"548332.19999999995","contractStartTime":"2016-09-10","rentTotal":"1230646.49","paymentType":"月付","period":"36 ","brandName":"巴拉巴拉","rentType":"固定租金","storeNo":"S5-3F-003","rentFreePeriod":"3","floorNo":"3","deductPercent":"","contractEndTime":"2019-09-09","commercialType":"儿童","contractId":"SYQBZZ16137","square":"234.33"},{"propertyFeeTotal":"648941.02","contractStartTime":"2016-09-10","rentTotal":"0","paymentType":"季付","period":"120 ","brandName":"星巴克","rentType":"提成租金","storeNo":"S1-1F-017,S1-2F-015","rentFreePeriod":"0","floorNo":"1,2","deductPercent":"9%","contractEndTime":"2026-09-09","commercialType":"餐饮","contractId":"SYQBZZ16155","square":"217.34"},{"propertyFeeTotal":"52884.63","contractStartTime":"2016-09-10","rentTotal":"224229.5","paymentType":"月付","period":"24 ","brandName":"零食多","rentType":"固定租金","storeNo":"B1-206","rentFreePeriod":"1","floorNo":"-1","deductPercent":"","contractEndTime":"2018-09-09","commercialType":"配套","contractId":"SYQBZZ16124","square":"33"},{"propertyFeeTotal":"927862.43","contractStartTime":"2016-09-10","rentTotal":"3244309.1","paymentType":"月付","period":"60 ","brandName":"逗蛙","rentType":"固定租金","storeNo":"S5-4F-003","rentFreePeriod":"3","floorNo":"4","deductPercent":"","contractEndTime":"2021-09-09","commercialType":"餐饮","contractId":"SYQBZZ16141","square":"234.97"},{"propertyFeeTotal":"57332.52","contractStartTime":"2016-09-10","rentTotal":"397440","paymentType":"月付","period":"36 ","brandName":"分子冰激凌","rentType":"固定租金","storeNo":"S1-1F-013","rentFreePeriod":"0","floorNo":"1","deductPercent":"","contractEndTime":"2019-09-09","commercialType":"餐饮","contractId":"SYQBZZ16129","square":"24"},{"propertyFeeTotal":"436509.61","contractStartTime":"2016-09-10","rentTotal":"1453872.37","paymentType":"月付","period":"36 ","brandName":"星期六","rentType":"固定租金","storeNo":"S4a-1F-009/001b","rentFreePeriod":"3","floorNo":"1","deductPercent":"","contractEndTime":"2019-09-09","commercialType":"配套","contractId":"SYQBZZ16191","square":"186.37"},{"propertyFeeTotal":"51480","contractStartTime":"2016-09-10","rentTotal":"257136","paymentType":"月付","period":"36 ","brandName":"香港十三座","rentType":"固定租金","storeNo":"B1-78b","rentFreePeriod":"0","floorNo":"-1","deductPercent":"","contractEndTime":"2019-09-09","commercialType":"餐饮","contractId":"SYQBZZ16196","square":"22"},{"propertyFeeTotal":"1438172.93","contractStartTime":"2016-09-10","rentTotal":"3417288.6","paymentType":"月付","period":"60 ","brandName":"巴实火锅","rentType":"固定租金","storeNo":"S1-1F-019b,S1-2F-016","rentFreePeriod":"3","floorNo":"1,2","deductPercent":"","contractEndTime":"2021-09-09","commercialType":"餐饮","contractId":"SYQBZZ16206","square":"364.2"},{"propertyFeeTotal":"39234.78","contractStartTime":"2016-09-10","rentTotal":"225944.64","paymentType":"月付","period":"24 ","brandName":"人在茶在茶饮店","rentType":"固定租金","storeNo":"S1-2F-012","rentFreePeriod":"0","floorNo":"2","deductPercent":"","contractEndTime":"2018-09-09","commercialType":"餐饮","contractId":"SYQBZZ16198","square":"24.84"},{"propertyFeeTotal":"305008.99","contractStartTime":"2016-09-10","rentTotal":"851114.88","paymentType":"月付","period":"36 ","brandName":"欧时力","rentType":"固定租金","storeNo":"S2-1F-002b","rentFreePeriod":"3","floorNo":"1","deductPercent":"","contractEndTime":"2019-09-09","commercialType":"服装","contractId":"SYQBZZ16256","square":"127.68"},{"propertyFeeTotal":"1931284.51","contractStartTime":"2016-09-10","rentTotal":"5327466.0599999996","paymentType":"月付","period":"60 ","brandName":"古炉","rentType":"固定租金","storeNo":"S4a-4F-001a","rentFreePeriod":"3","floorNo":"4","deductPercent":"","contractEndTime":"2021-09-09","commercialType":"餐饮","contractId":"SYQBZZ16215","square":"493.01"},{"propertyFeeTotal":"1323594","contractStartTime":"2016-09-16","rentTotal":"4749864.1399999997","paymentType":"月付","period":"60 ","brandName":"徽语","rentType":"固定租金","storeNo":"S2-4F-001a,S2-4F-001b-1","rentFreePeriod":"4","floorNo":"4","deductPercent":"","contractEndTime":"2021-09-15","commercialType":"餐饮","contractId":"SYQBZZ16224","square":"735.33"},{"propertyFeeTotal":"412500","contractStartTime":"2016-09-10","rentTotal":"2778554.17","paymentType":"月付","period":"60 ","brandName":"度小月生活馆","rentType":"固定租金","storeNo":"H3d-1F-001/005","rentFreePeriod":"6","floorNo":"1","deductPercent":"","contractEndTime":"2021-09-09","commercialType":"餐饮","contractId":"SYQBZZ16229","square":"275"},{"propertyFeeTotal":"447720","contractStartTime":"2016-09-10","rentTotal":"1206930.67","paymentType":"月付","period":"60 ","brandName":"巴黎贝甜","rentType":"固定租金","storeNo":"S1-1F-007","rentFreePeriod":"5","floorNo":"1","deductPercent":"","contractEndTime":"2021-09-09","commercialType":"餐饮","contractId":"SYQBZZ16226","square":"114.8"},{"propertyFeeTotal":"322853.74","contractStartTime":"2016-09-10","rentTotal":"729674.85","paymentType":"月付","period":"36 ","brandName":"伊芙丽","rentType":"固定租金","storeNo":"S2-1F-002a","rentFreePeriod":"3","floorNo":"1","deductPercent":"","contractEndTime":"2019-09-09","commercialType":"服装","contractId":"SYQBZZ16228","square":"135.15"},{"propertyFeeTotal":"252655.26","contractStartTime":"2016-09-10","rentTotal":"697768.97","paymentType":"月付","period":"36 ","brandName":"丽芙泰勒","rentType":"固定租金","storeNo":"S2-2F-001b-1","rentFreePeriod":"3","floorNo":"2","deductPercent":"","contractEndTime":"2019-09-09","commercialType":"配套","contractId":"SYQBZZ16240","square":"107.08"},{"propertyFeeTotal":"621900","contractStartTime":"2016-09-10","rentTotal":"5027716","paymentType":"月付","period":"60 ","brandName":"阳家私坊毛肚火锅","rentType":"固定租金","storeNo":"H2c-1F-008,H2c-2F-006,H2c-3F-002","rentFreePeriod":"3","floorNo":"1,2,3","deductPercent":"","contractEndTime":"2021-09-09","commercialType":"餐饮","contractId":"SYQBZZ16236","square":"414.6"},{"propertyFeeTotal":"113070.32","contractStartTime":"2016-09-10","rentTotal":"356038.48","paymentType":"月付","period":"24 ","brandName":"格兰玛弗兰","rentType":"固定租金","storeNo":"S3-1F-001c","rentFreePeriod":"2","floorNo":"1","deductPercent":"","contractEndTime":"2018-09-09","commercialType":"配套","contractId":"SYQBZZ16233","square":"70.28"},{"propertyFeeTotal":"110769.66","contractStartTime":"2016-09-10","rentTotal":"277327.8","paymentType":"季付","period":"24 ","brandName":"芭妮兰","rentType":"两者取高","storeNo":"S3-1F-001b","rentFreePeriod":"2","floorNo":"1","deductPercent":"","contractEndTime":"2018-09-09","commercialType":"配套","contractId":"SYQBZZ16266","square":"68.849999999999994"},{"propertyFeeTotal":"27286.18","contractStartTime":"2016-09-10","rentTotal":"128048","paymentType":"月付","period":"24 ","brandName":"大通冰室","rentType":"固定租金","storeNo":"S4a-4F-003","rentFreePeriod":"2","floorNo":"4","deductPercent":"","contractEndTime":"2018-09-09","commercialType":"餐饮","contractId":"SYQBZZ16239","square":"16.690000000000001"},{"propertyFeeTotal":"387630","contractStartTime":"2016-09-10","rentTotal":"2439527.87","paymentType":"月付","period":"60 ","brandName":"在马里奥","rentType":"固定租金","storeNo":"S4a-1F-001c,S4a-2F-001b,S4a-2F-002c","rentFreePeriod":"3","floorNo":"1,2","deductPercent":"","contractEndTime":"2021-09-09","commercialType":"餐饮","contractId":"SYQBZZ16237","square":"258.42"},{"propertyFeeTotal":"4180420.84","contractStartTime":"2016-09-10","rentTotal":"12463200","paymentType":"季付","period":"120 ","brandName":"U&R","rentType":"两者取高","storeNo":"S1-1F-010/011/012c","rentFreePeriod":"3","floorNo":"1","deductPercent":"","contractEndTime":"2026-09-09","commercialType":"服装","contractId":"SYQBZZ16254","square":"1154"},{"propertyFeeTotal":"102564.13","contractStartTime":"2016-09-10","rentTotal":"313632","paymentType":"月付","period":"24 ","brandName":"公牛巨人","rentType":"固定租金","storeNo":"B1-211,B1-213","rentFreePeriod":"3","floorNo":"-1","deductPercent":"","contractEndTime":"2018-09-09","commercialType":"配套","contractId":"SYQBZZ16249","square":"64"},{"propertyFeeTotal":"316602.21000000002","contractStartTime":"2016-09-10","rentTotal":"970501","paymentType":"月付","period":"36 ","brandName":"美丽档案","rentType":"固定租金","storeNo":"B1-50,B1-52,B1-54,B1-56,B1-66","rentFreePeriod":"3","floorNo":"-1","deductPercent":"","contractEndTime":"2019-09-09","commercialType":"服装","contractId":"SYQBZZ16268","square":"133"},{"propertyFeeTotal":"168480","contractStartTime":"2016-09-10","rentTotal":"619704","paymentType":"月付","period":"36 ","brandName":"香港杏记甜品","rentType":"固定租金","storeNo":"S3-1F-005","rentFreePeriod":"2","floorNo":"1","deductPercent":"","contractEndTime":"2019-09-09","commercialType":"餐饮","contractId":"SYQBZZ16269","square":"72"},{"propertyFeeTotal":"26063.45","contractStartTime":"2016-09-10","rentTotal":"136296","paymentType":"月付","period":"24 ","brandName":"茶桔便","rentType":"固定租金","storeNo":"S3-4F-002","rentFreePeriod":"3","floorNo":"4","deductPercent":"","contractEndTime":"2018-09-09","commercialType":"餐饮","contractId":"SYQBZZ16273","square":"16.2"},{"propertyFeeTotal":"525891.6","contractStartTime":"2016-09-10","rentTotal":"1144765.53","paymentType":"月付","period":"36 ","brandName":"微软","rentType":"固定租金","storeNo":"S2-1F-003","rentFreePeriod":"3","floorNo":"1","deductPercent":"","contractEndTime":"2019-09-09","commercialType":"配套","contractId":"SYQBZZ16282","square":"224.74"},{"propertyFeeTotal":"216450","contractStartTime":"2016-09-10","rentTotal":"1081664.17","paymentType":"月付","period":"36 ","brandName":"女王之宠","rentType":"固定租金","storeNo":"S3-1F-001e","rentFreePeriod":"3","floorNo":"1","deductPercent":"","contractEndTime":"2019-09-09","commercialType":"餐饮","contractId":"SYQBZZ16279","square":"92.5"},{"propertyFeeTotal":"31326","contractStartTime":"2016-09-10","rentTotal":"200799.66","paymentType":"月付","period":"24 ","brandName":"烘焙实验室","rentType":"固定租金","storeNo":"T2-48","rentFreePeriod":"3","floorNo":"1","deductPercent":"","contractEndTime":"2018-09-09","commercialType":"餐饮","contractId":"SYQBZZ16287","square":"52.21"},{"propertyFeeTotal":"487470","contractStartTime":"2016-09-10","rentTotal":"4231564.58","paymentType":"月付","period":"60 ","brandName":"麦娜杰瑞","rentType":"固定租金","storeNo":"T2-18,T2-20,T2-22,T2-24,T2-26,T2-437","rentFreePeriod":"3","floorNo":"1","deductPercent":"","contractEndTime":"2021-09-09","commercialType":"儿童","contractId":"SYQBZZ16286","square":"324.98"},{"propertyFeeTotal":"841544","contractStartTime":"2016-09-10","rentTotal":"0","paymentType":"季付","period":"96 ","brandName":"屈臣氏","rentType":"提成租金","storeNo":"B1-199-200/205/204/69-73","rentFreePeriod":"0","floorNo":"-1","deductPercent":"6%","contractEndTime":"2024-09-09","commercialType":"配套","contractId":"SYQBZZ16294","square":"292"},{"propertyFeeTotal":"720135","contractStartTime":"2016-09-10","rentTotal":"3847681.3","paymentType":"月付","period":"60 ","brandName":"WARAWARA","rentType":"固定租金","storeNo":"S4b-2F-001,S4b-1F-001","rentFreePeriod":"6","floorNo":"1,2","deductPercent":"","contractEndTime":"2021-09-09","commercialType":"餐饮","contractId":"SYQBZZ16295","square":"480.09"},{"propertyFeeTotal":"103194","contractStartTime":"2016-09-10","rentTotal":"397657.05","paymentType":"月付","period":"36 ","brandName":"贝尔多爸爸","rentType":"固定租金","storeNo":"B1-62","rentFreePeriod":"3","floorNo":"-1","deductPercent":"","contractEndTime":"2019-09-09","commercialType":"餐饮","contractId":"SYQBZZ16308","square":"44.1"},{"propertyFeeTotal":"35334","contractStartTime":"2016-09-10","rentTotal":"114337.2","paymentType":"月付","period":"24 ","brandName":"ROC ON SKY","rentType":"固定租金","storeNo":"S1-3F-002","rentFreePeriod":"3","floorNo":"3","deductPercent":"","contractEndTime":"2018-09-09","commercialType":"配套","contractId":"SYQBZZ16319","square":"22.65"},{"propertyFeeTotal":"589375.80000000005","contractStartTime":"2016-09-10","rentTotal":"1671493.28","paymentType":"月付","period":"36 ","brandName":"AOK MART","rentType":"固定租金","storeNo":"S3-2F-001c/002-1/002c","rentFreePeriod":"3","floorNo":"2","deductPercent":"","contractEndTime":"2019-09-09","commercialType":"服装","contractId":"SYQBZZ16322","square":"251.87"},{"propertyFeeTotal":"51483.35","contractStartTime":"2016-09-10","rentTotal":"159104","paymentType":"月付","period":"24 ","brandName":"唐三丈腊汁肉夹馍","rentType":"固定租金","storeNo":"B1-203","rentFreePeriod":"2","floorNo":"-1","deductPercent":"","contractEndTime":"2018-09-09","commercialType":"餐饮","contractId":"SYQBZZ16351","square":"32"},{"propertyFeeTotal":"128700","contractStartTime":"2016-09-10","rentTotal":"910800","paymentType":"月付","period":"36 ","brandName":"鹅颈桥","rentType":"固定租金","storeNo":"S2-1F-006b-2","rentFreePeriod":"0","floorNo":"1","deductPercent":"","contractEndTime":"2019-09-09","commercialType":"餐饮","contractId":"SYQBZZ16385","square":"55"},{"propertyFeeTotal":"46872","contractStartTime":"2016-09-10","rentTotal":"397708.92","paymentType":"月付","period":"36 ","brandName":"吧块吧","rentType":"固定租金","storeNo":"T3-405","rentFreePeriod":"3","floorNo":"1","deductPercent":"","contractEndTime":"2019-09-09","commercialType":"餐饮","contractId":"SYQBZZ16399","square":"52.08"},{"propertyFeeTotal":"31334.799999999999","contractStartTime":"2016-09-10","rentTotal":"249775.68","paymentType":"月付","period":"24 ","brandName":"面爷爷老面馆","rentType":"固定租金","storeNo":"T3-407","rentFreePeriod":"2","floorNo":"1","deductPercent":"","contractEndTime":"2018-09-09","commercialType":"餐饮","contractId":"SYQBZZ16400","square":"52.08"},{"propertyFeeTotal":"1336920","contractStartTime":"2016-09-10","rentTotal":"2788106.67","paymentType":"月付","period":"60 ","brandName":"胖哥俩肉蟹煲","rentType":"固定租金","storeNo":"S4a-4F-001b/002","rentFreePeriod":"5","floorNo":"4","deductPercent":"","contractEndTime":"2021-09-09","commercialType":"餐饮","contractId":"SYQBZZ15049","square":"342.8"},{"propertyFeeTotal":"3186877.52","contractStartTime":"2017-01-17","rentTotal":"16185102.189999999","paymentType":"季付","period":"120 ","brandName":"银乐迪","rentType":"固定租金","storeNo":"S1-3F-001/003/005/006a-1/006b-2","rentFreePeriod":"3","floorNo":"3","deductPercent":"","contractEndTime":"2027-01-16","commercialType":"配套","contractId":"SYQBZZ16093","square":"1976.93"},{"propertyFeeTotal":"1398891","contractStartTime":"2016-09-10","rentTotal":"3827162.52","paymentType":"月付","period":"60 ","brandName":"川掌门","rentType":"固定租金","storeNo":"S1-1F-020a,S1-1F-021","rentFreePeriod":"3","floorNo":"1","deductPercent":"","contractEndTime":"2021-09-09","commercialType":"餐饮","contractId":"SYQBZZ16101","square":"358.69"},{"propertyFeeTotal":"167219.84","contractStartTime":"2016-09-10","rentTotal":"529200","paymentType":"月付","period":"36 ","brandName":"和风铁板烧","rentType":"固定租金","storeNo":"B1-169,B1-170","rentFreePeriod":"0","floorNo":"-1","deductPercent":"","contractEndTime":"2019-09-09","commercialType":"餐饮","contractId":"SYQBZZ16086","square":"70"},{"propertyFeeTotal":"100182.45","contractStartTime":"2016-09-10","rentTotal":"593658","paymentType":"月付","period":"60 ","brandName":"希望先生","rentType":"固定租金","storeNo":"S5-4F-002","rentFreePeriod":"0","floorNo":"4","deductPercent":"","contractEndTime":"2021-09-09","commercialType":"餐饮","contractId":"SYQBZZ16089","square":"25.37"},{"propertyFeeTotal":"222975","contractStartTime":"2016-09-10","rentTotal":"1887855","paymentType":"月付","period":"36 ","brandName":"墨上品","rentType":"固定租金","storeNo":"T1-58,T1-60,T1-62,T1-64,T1-66","rentFreePeriod":"0","floorNo":"1","deductPercent":"","contractEndTime":"2019-09-09","commercialType":"配套","contractId":"SYQBZZ16087","square":"247.75"},{"propertyFeeTotal":"52953.82","contractStartTime":"2016-09-10","rentTotal":"151734","paymentType":"月付","period":"24 ","brandName":"思乐得","rentType":"固定租金","storeNo":"B1-74","rentFreePeriod":"2","floorNo":"-1","deductPercent":"","contractEndTime":"2018-09-09","commercialType":"配套","contractId":"SYQBZZ16088","square":"33"},{"propertyFeeTotal":"621855","contractStartTime":"2016-09-10","rentTotal":"5472324","paymentType":"月付","period":"60 ","brandName":"懂锅","rentType":"固定租金","storeNo":"T1-82,T1-84,T1-86,T1-88,T1-90,T1-92","rentFreePeriod":"0","floorNo":"1","deductPercent":"","contractEndTime":"2021-09-09","commercialType":"餐饮","contractId":"SYQBZZ16085","square":"414.57"},{"propertyFeeTotal":"4334803.2","contractStartTime":"2016-09-10","rentTotal":"11855446.01","paymentType":"季付","period":"96 ","brandName":"宝大祥","rentType":"两者取高","storeNo":"S4b-3F-001/006,S4b-3F-002a","rentFreePeriod":"3","floorNo":"3","deductPercent":"","contractEndTime":"2024-09-09","commercialType":"儿童","contractId":"SYQBZZ16091","square":"1505.14"},{"propertyFeeTotal":"2184000","contractStartTime":"2016-09-10","rentTotal":"4229194.67","paymentType":"月付","period":"60 ","brandName":"匆匆那","rentType":"固定租金","storeNo":"S4b-4F-001b/002a/002b-1","rentFreePeriod":"3","floorNo":"4","deductPercent":"","contractEndTime":"2021-09-09","commercialType":"餐饮","contractId":"SYQBZZ16245","square":"560"},{"propertyFeeTotal":"2375568","contractStartTime":"2016-09-10","rentTotal":"0","paymentType":"季付","period":"120 ","brandName":"无印良品","rentType":"提成租金","storeNo":"S1-1F-012b/019c","rentFreePeriod":"6","floorNo":"1","deductPercent":"7%","contractEndTime":"2026-09-09","commercialType":"服装","contractId":"SYQBZZ16126","square":"733.2"},{"propertyFeeTotal":"622518","contractStartTime":"2016-09-10","rentTotal":"1523572.9","paymentType":"季付","period":"60 ","brandName":"斯莱德","rentType":"两者取高","storeNo":"S4b-2F-006","rentFreePeriod":"6","floorNo":"2","deductPercent":"","contractEndTime":"2021-09-09","commercialType":"服装","contractId":"SYQBZZ16096","square":"159.62"},{"propertyFeeTotal":"183952.71","contractStartTime":"2016-09-10","rentTotal":"1577144.39","paymentType":"月付","period":"36 ","brandName":"孜苒","rentType":"固定租金","storeNo":"T1-100,T1-94,T1-96,T1-98","rentFreePeriod":"0","floorNo":"1","deductPercent":"","contractEndTime":"2019-09-09","commercialType":"餐饮","contractId":"SYQBZZ16094","square":"203.45"},{"propertyFeeTotal":"54910.22","contractStartTime":"2016-09-10","rentTotal":"416437.19","paymentType":"月付","period":"24 ","brandName":"林清轩","rentType":"固定租金","storeNo":"S2-1F-010","rentFreePeriod":"3","floorNo":"1","deductPercent":"","contractEndTime":"2018-09-09","commercialType":"配套","contractId":"SYQBZZ16099","square":"34.130000000000003"},{"propertyFeeTotal":"2172300","contractStartTime":"2016-09-10","rentTotal":"4610883.13","paymentType":"月付","period":"60 ","brandName":"金宝贝","rentType":"固定租金","storeNo":"S4a-3F-002-2,S4a-3F-003","rentFreePeriod":"3","floorNo":"3","deductPercent":"","contractEndTime":"2021-09-09","commercialType":"儿童","contractId":"SYQBZZ16097","square":"557"},{"propertyFeeTotal":"2414250.87","contractStartTime":"2016-09-10","rentTotal":"4771617.1100000003","paymentType":"季付","period":"60 ","brandName":"VERO MODA","rentType":"两者取高","storeNo":"S4b-1F-007a,S4b-1F-008d,S4b-1F-007b-1,S4b-2F-008","rentFreePeriod":"6","floorNo":"1,2","deductPercent":"","contractEndTime":"2021-09-09","commercialType":"服装","contractId":"SYQBZZ16176","square":"611.38"},{"propertyFeeTotal":"5522548.5300000003","contractStartTime":"2016-09-10","rentTotal":"12390379.810000001","paymentType":"季付","period":"96 ","brandName":"旖彩城","rentType":"两者取高","storeNo":"S1-2F-002/003/005/009/010/011","rentFreePeriod":"6","floorNo":"2","deductPercent":"","contractEndTime":"2024-09-09","commercialType":"服装","contractId":"SYQBZZ16123","square":"1909.02"},{"propertyFeeTotal":"97461","contractStartTime":"2016-09-10","rentTotal":"752777.94","paymentType":"月付","period":"36 ","brandName":"罗帝可可","rentType":"固定租金","storeNo":"T2-50,T2-52","rentFreePeriod":"1","floorNo":"1","deductPercent":"","contractEndTime":"2019-09-09","commercialType":"餐饮","contractId":"SYQBZZ16132","square":"108.29"},{"propertyFeeTotal":"151349.25","contractStartTime":"2016-09-10","rentTotal":"541800","paymentType":"月付","period":"36 ","brandName":"黛慕","rentType":"固定租金","storeNo":"B1-42,B1-44","rentFreePeriod":"2","floorNo":"-1","deductPercent":"","contractEndTime":"2019-09-09","commercialType":"配套","contractId":"SYQBZZ16134","square":"64.5"},{"propertyFeeTotal":"1160144.17","contractStartTime":"2016-09-10","rentTotal":"5998030.5","paymentType":"月付","period":"60 ","brandName":"懒咖","rentType":"固定租金","storeNo":"T5-1F-005a/005b,T5-2F-002","rentFreePeriod":"0","floorNo":"1,2","deductPercent":"","contractEndTime":"2021-09-09","commercialType":"餐饮","contractId":"SYQBZZ16130","square":"865.78"},{"propertyFeeTotal":"1866852","contractStartTime":"2016-09-10","rentTotal":"3969964.5","paymentType":"月付","period":"60 ","brandName":"玲珑我家酸菜鱼","rentType":"固定租金","storeNo":"S1-1F-020c,S1-2F-017,S1-2F-018","rentFreePeriod":"3","floorNo":"1,2","deductPercent":"","contractEndTime":"2021-09-09","commercialType":"餐饮","contractId":"SYQBZZ16139","square":"478.68"},{"propertyFeeTotal":"515895","contractStartTime":"2016-09-10","rentTotal":"3491474.19","paymentType":"月付","period":"60 ","brandName":"丰盛胡同","rentType":"固定租金","storeNo":"H3b-1F-001,H3b-2F-001","rentFreePeriod":"6","floorNo":"1,2","deductPercent":"","contractEndTime":"2021-09-09","commercialType":"餐饮","contractId":"SYQBZZ16165","square":"343.93"},{"propertyFeeTotal":"359424","contractStartTime":"2016-09-10","rentTotal":"1067801.6000000001","paymentType":"月付","period":"36 ","brandName":"极浓博多","rentType":"固定租金","storeNo":"B1-59,B1-60,B1-61","rentFreePeriod":"3","floorNo":"-1","deductPercent":"","contractEndTime":"2019-09-09","commercialType":"餐饮","contractId":"SYQBZZ16143","square":"153.6"},{"propertyFeeTotal":"53482","contractStartTime":"2016-09-10","rentTotal":"231024.33","paymentType":"月付","period":"24 ","brandName":"臻轩坊","rentType":"固定租金","storeNo":"B1-207","rentFreePeriod":"1","floorNo":"-1","deductPercent":"","contractEndTime":"2018-09-09","commercialType":"配套","contractId":"SYQBZZ16133","square":"34"},{"propertyFeeTotal":"29016","contractStartTime":"2016-09-10","rentTotal":"206070.02","paymentType":"月付","period":"24 ","brandName":"了一茶莊","rentType":"固定租金","storeNo":"T3-8","rentFreePeriod":"1","floorNo":"1","deductPercent":"","contractEndTime":"2018-09-09","commercialType":"配套","contractId":"SYQBZZ16131","square":"48.36"},{"propertyFeeTotal":"96796.4","contractStartTime":"2016-09-10","rentTotal":"612743.43999999994","paymentType":"月付","period":"36 ","brandName":"阿吉豆","rentType":"固定租金","storeNo":"S4a-1F-005","rentFreePeriod":"3","floorNo":"1","deductPercent":"","contractEndTime":"2019-09-09","commercialType":"配套","contractId":"SYQBZZ16135","square":"40.520000000000003"},{"propertyFeeTotal":"74007.320000000007","contractStartTime":"2016-09-10","rentTotal":"375521","paymentType":"月付","period":"24 ","brandName":"美素","rentType":"固定租金","storeNo":"S1-1F-009","rentFreePeriod":"3","floorNo":"1","deductPercent":"","contractEndTime":"2018-09-09","commercialType":"配套","contractId":"SYQBZZ16146","square":"46"},{"propertyFeeTotal":"40816.65","contractStartTime":"2016-09-10","rentTotal":"139492.72","paymentType":"月付","period":"24 ","brandName":"妮欧美甲","rentType":"固定租金","storeNo":"S5-3F-005","rentFreePeriod":"3","floorNo":"3","deductPercent":"","contractEndTime":"2018-09-09","commercialType":"配套","contractId":"SYQBZZ16147","square":"25.37"},{"propertyFeeTotal":"32760","contractStartTime":"2016-09-10","rentTotal":"181440","paymentType":"月付","period":"36 ","brandName":"鲜之恋情榨汁","rentType":"固定租金","storeNo":"B1-78a","rentFreePeriod":"0","floorNo":"-1","deductPercent":"","contractEndTime":"2019-09-09","commercialType":"餐饮","contractId":"SYQBZZ16193","square":"14"},{"propertyFeeTotal":"56854.75","contractStartTime":"2016-09-10","rentTotal":"423960.51","paymentType":"月付","period":"36 ","brandName":"瑞蜜可","rentType":"固定租金","storeNo":"S3-1F-002","rentFreePeriod":"3","floorNo":"1","deductPercent":"","contractEndTime":"2019-09-09","commercialType":"餐饮","contractId":"SYQBZZ16144","square":"23.8"},{"propertyFeeTotal":"1830685.21","contractStartTime":"2016-09-10","rentTotal":"14573155.84","paymentType":"月付","period":"72 ","brandName":"蒋记海鲜","rentType":"固定租金","storeNo":"H2c-1F-001/002/005,H2c-1F-003,H2c-2F-001/002/003,H2c-3F-001","rentFreePeriod":"6","floorNo":"1,2,3","deductPercent":"","contractEndTime":"2022-09-09","commercialType":"餐饮","contractId":"SYQBZZ16150","square":"1006.54"},{"propertyFeeTotal":"2494368","contractStartTime":"2017-01-01","rentTotal":"9977472","paymentType":"月付","period":"60 ","brandName":"益德网咖","rentType":"固定租金","storeNo":"T3-1F-10,T3-2F","rentFreePeriod":"3","floorNo":"1,2","deductPercent":"","contractEndTime":"2021-12-31","commercialType":"配套","contractId":"SYQBZZ16162","square":"1385.76"},{"propertyFeeTotal":"5577300","contractStartTime":"2016-09-10","rentTotal":"14495557.609999999","paymentType":"季付","period":"120 ","brandName":"地球尔","rentType":"固定租金","storeNo":"S2-3F-001a,S2-3F-001b,S2-3F-001c,S2-3F-001d,S2-3F-002-2,S2-3F-003-2","rentFreePeriod":"6","floorNo":"3","deductPercent":"","contractEndTime":"2026-09-09","commercialType":"儿童","contractId":"SYQBZZ16158","square":"1549.25"},{"propertyFeeTotal":"428520","contractStartTime":"2016-09-10","rentTotal":"2489367.91","paymentType":"月付","period":"60 ","brandName":"青木瓜之味","rentType":"固定租金","storeNo":"H3e-1F-001,H3e-2F-001","rentFreePeriod":"3","floorNo":"1,2","deductPercent":"","contractEndTime":"2021-09-09","commercialType":"餐饮","contractId":"SYQBZZ16161","square":"285.68"},{"propertyFeeTotal":"443219.92","contractStartTime":"2016-09-10","rentTotal":"1595183.04","paymentType":"月付","period":"60 ","brandName":"德味家","rentType":"固定租金","storeNo":"B1-77,B1-81,B1-83","rentFreePeriod":"0","floorNo":"-1","deductPercent":"","contractEndTime":"2021-09-09","commercialType":"餐饮","contractId":"SYQBZZ16163","square":"113.52"},{"propertyFeeTotal":"57689.78","contractStartTime":"2016-09-10","rentTotal":"243381","paymentType":"月付","period":"36 ","brandName":"可C可T","rentType":"固定租金","storeNo":"S1-3F-007","rentFreePeriod":"3","floorNo":"3","deductPercent":"","contractEndTime":"2019-09-09","commercialType":"餐饮","contractId":"SYQBZZ16174","square":"24.45"},{"propertyFeeTotal":"385754.18","contractStartTime":"2016-09-10","rentTotal":"3761216.22","paymentType":"月付","period":"60 ","brandName":"溪雨观","rentType":"固定租金","storeNo":"T4-3,T4-5,T4-395,T4-397","rentFreePeriod":"3","floorNo":"1","deductPercent":"","contractEndTime":"2021-09-09","commercialType":"餐饮","contractId":"SYQBZZ16157","square":"255.89"},{"propertyFeeTotal":"816180","contractStartTime":"2016-09-10","rentTotal":"7344477.3399999999","paymentType":"月付","period":"60 ","brandName":"悦宝园","rentType":"固定租金","storeNo":"T3-12,T3-14,T3-417,T3-419,T3-421,T3-423,T3-425,T3-427,T3-429","rentFreePeriod":"3","floorNo":"1","deductPercent":"","contractEndTime":"2021-09-09","commercialType":"儿童","contractId":"SYQBZZ16172","square":"544.12"},{"propertyFeeTotal":"111320.64","contractStartTime":"2016-09-10","rentTotal":"262824","paymentType":"季付","period":"36 ","brandName":"酷猫","rentType":"两者取高","storeNo":"S1-2F-013","rentFreePeriod":"2","floorNo":"2","deductPercent":"","contractEndTime":"2019-09-09","commercialType":"配套","contractId":"SYQBZZ16179","square":"46.6"},{"propertyFeeTotal":"130670.93","contractStartTime":"2016-09-10","rentTotal":"915776.4","paymentType":"月付","period":"36 ","brandName":"锅品面吧","rentType":"固定租金","storeNo":"T1-78","rentFreePeriod":"0","floorNo":"1","deductPercent":"","contractEndTime":"2019-09-09","commercialType":"餐饮","contractId":"SYQBZZ16180","square":"143.99"},{"propertyFeeTotal":"24084.560000000001","contractStartTime":"2016-09-10","rentTotal":"110478.6","paymentType":"月付","period":"24 ","brandName":"迈茶","rentType":"固定租金","storeNo":"S4a-2F-005","rentFreePeriod":"0","floorNo":"2","deductPercent":"","contractEndTime":"2018-09-09","commercialType":"餐饮","contractId":"SYQBZZ16187","square":"14.97"},{"propertyFeeTotal":"24068.47","contractStartTime":"2016-09-10","rentTotal":"87108.08","paymentType":"月付","period":"24 ","brandName":"加减橙厨","rentType":"固定租金","storeNo":"S4a-3F-005b","rentFreePeriod":"3","floorNo":"3","deductPercent":"","contractEndTime":"2018-09-09","commercialType":"餐饮","contractId":"SYQBZZ16189","square":"14.96"},{"propertyFeeTotal":"4788937.5999999996","contractStartTime":"2016-11-07","rentTotal":"6213117.5700000003","paymentType":"季付","period":"120 ","brandName":"UA","rentType":"两者取高","storeNo":"S5-2F-004,S5-1F-003","rentFreePeriod":"6","floorNo":"1,2","deductPercent":"","contractEndTime":"2026-11-06","commercialType":"服装","contractId":"SYQBZZ16190","square":"605.39"},{"propertyFeeTotal":"235733.33","contractStartTime":"2016-09-10","rentTotal":"819000","paymentType":"月付","period":"36 ","brandName":"水星家纺","rentType":"固定租金","storeNo":"B1-208,B1-210,B1-212","rentFreePeriod":"2","floorNo":"-1","deductPercent":"","contractEndTime":"2019-09-09","commercialType":"配套","contractId":"SYQBZZ16188","square":"100"},{"propertyFeeTotal":"1618383","contractStartTime":"2016-09-10","rentTotal":"4450829.9000000004","paymentType":"月付","period":"60 ","brandName":"岳阳楼湘","rentType":"固定租金","storeNo":"S4b-4F-002b-2","rentFreePeriod":"4","floorNo":"4","deductPercent":"","contractEndTime":"2021-09-09","commercialType":"餐饮","contractId":"SYQBZZ16194","square":"414.97"},{"propertyFeeTotal":"315257.18","contractStartTime":"2016-09-10","rentTotal":"877160.6","paymentType":"月付","period":"36 ","brandName":"Lagogo","rentType":"固定租金","storeNo":"S2-2F-003","rentFreePeriod":"4","floorNo":"2","deductPercent":"","contractEndTime":"2019-09-09","commercialType":"服装","contractId":"SYQBZZ16208","square":"131.97"},{"propertyFeeTotal":"228732.86","contractStartTime":"2016-09-10","rentTotal":"636418.32999999996","paymentType":"月付","period":"36 ","brandName":"海天空","rentType":"固定租金","storeNo":"S2-2F-002b-1","rentFreePeriod":"4","floorNo":"2","deductPercent":"","contractEndTime":"2019-09-09","commercialType":"服装","contractId":"SYQBZZ16210","square":"95.75"},{"propertyFeeTotal":"1437383.16","contractStartTime":"2016-09-10","rentTotal":"3107468","paymentType":"月付","period":"60 ","brandName":"小辉哥","rentType":"固定租金","storeNo":"S2-4F-002b","rentFreePeriod":"6","floorNo":"4","deductPercent":"","contractEndTime":"2021-09-09","commercialType":"餐饮","contractId":"SYQBZZ16201","square":"364"},{"propertyFeeTotal":"430192.9","contractStartTime":"2016-09-10","rentTotal":"988110.93","paymentType":"月付","period":"36 ","brandName":"韦哲国际创意中心","rentType":"固定租金","storeNo":"S2-3F-005,S2-3F-003-1","rentFreePeriod":"3","floorNo":"3","deductPercent":"","contractEndTime":"2019-09-09","commercialType":"儿童","contractId":"SYQBZZ16195","square":"180.4"},{"propertyFeeTotal":"1281300","contractStartTime":"2016-09-10","rentTotal":"9384241.1999999993","paymentType":"季付","period":"60 ","brandName":"音乐天空","rentType":"固定租金","storeNo":"H3d-1F-002/003,H3d-2F-001/002/003,H3d-3F-001","rentFreePeriod":"4","floorNo":"1,2,3","deductPercent":"","contractEndTime":"2021-09-09","commercialType":"餐饮","contractId":"SYQBZZ16209","square":"854.2"},{"propertyFeeTotal":"1397760","contractStartTime":"2016-09-10","rentTotal":"3019161.6000000001","paymentType":"月付","period":"60 ","brandName":"热风","rentType":"两者取高","storeNo":"S4b-2F-007","rentFreePeriod":"0","floorNo":"2","deductPercent":"","contractEndTime":"2021-09-09","commercialType":"配套","contractId":"SYQBZZ16214","square":"358.4"},{"propertyFeeTotal":"291655.28999999998","contractStartTime":"2016-09-10","rentTotal":"1175014.5","paymentType":"季付","period":"36 ","brandName":"金数码","rentType":"固定租金","storeNo":"S4b-1F-008a,S4b-1F-008c","rentFreePeriod":"3","floorNo":"1","deductPercent":"","contractEndTime":"2019-09-09","commercialType":"配套","contractId":"SYQBZZ16218","square":"122.09"},{"propertyFeeTotal":"36393.08","contractStartTime":"2016-09-10","rentTotal":"157213.65","paymentType":"月付","period":"24 ","brandName":"T400","rentType":"固定租金","storeNo":"S1-2F-008","rentFreePeriod":"3","floorNo":"2","deductPercent":"","contractEndTime":"2018-09-09","commercialType":"配套","contractId":"SYQBZZ16217","square":"22.65"},{"propertyFeeTotal":"246792.6","contractStartTime":"2016-09-10","rentTotal":"899623.48","paymentType":"月付","period":"36 ","brandName":"听说","rentType":"固定租金","storeNo":"S2-2F-002a-1","rentFreePeriod":"3","floorNo":"2","deductPercent":"","contractEndTime":"2019-09-09","commercialType":"服装","contractId":"SYQBZZ16230","square":"103.31"},{"propertyFeeTotal":"24458.2","contractStartTime":"2016-09-10","rentTotal":"398872.31","paymentType":"月付","period":"36 ","brandName":"都可茶饮","rentType":"固定租金","storeNo":"T5-1F-006","rentFreePeriod":"3","floorNo":"1","deductPercent":"","contractEndTime":"2019-09-09","commercialType":"餐饮","contractId":"SYQBZZ16246","square":"26.62"},{"propertyFeeTotal":"0","contractStartTime":"2016-09-10","rentTotal":"0","paymentType":"季付","period":"36 ","brandName":"江南布衣","rentType":"提成租金","storeNo":"S4b-1F-006,S4b-1F-007c,S4b-1F-007b-2","rentFreePeriod":"3","floorNo":"1","deductPercent":"11%","contractEndTime":"2019-09-09","commercialType":"服装","contractId":"SYQBZZ16289","square":"353.23"},{"propertyFeeTotal":"312000","contractStartTime":"2016-09-10","rentTotal":"0","paymentType":"季付","period":"120 ","brandName":"汉堡王","rentType":"提成租金","storeNo":"S4b-1F-003","rentFreePeriod":"0","floorNo":"1","deductPercent":"9%","contractEndTime":"2026-09-09","commercialType":"餐饮","contractId":"SYQBZZ16255","square":"260"},{"propertyFeeTotal":"1442107.33","contractStartTime":"2016-09-10","rentTotal":"2699312","paymentType":"月付","period":"72 ","brandName":"云海肴","rentType":"固定租金","storeNo":"S2-4F-002a/001b-2","rentFreePeriod":"6","floorNo":"4","deductPercent":"","contractEndTime":"2022-09-09","commercialType":"餐饮","contractId":"SYQBZZ16325","square":"308"},{"propertyFeeTotal":"163044","contractStartTime":"2016-09-10","rentTotal":"1413048","paymentType":"月付","period":"36 ","brandName":"上童官","rentType":"固定租金","storeNo":"T2-42,T2-44,T2-46","rentFreePeriod":"0","floorNo":"1","deductPercent":"","contractEndTime":"2019-09-09","commercialType":"餐饮","contractId":"SYQBZZ16265","square":"181.16"},{"propertyFeeTotal":"217309.95","contractStartTime":"2016-09-10","rentTotal":"751536","paymentType":"月付","period":"36 ","brandName":"尊客来","rentType":"固定租金","storeNo":"B1-82,B1-84","rentFreePeriod":"0","floorNo":"-1","deductPercent":"","contractEndTime":"2019-09-09","commercialType":"餐饮","contractId":"SYQBZZ16263","square":"92.1"},{"propertyFeeTotal":"17697.400000000001","contractStartTime":"2016-09-10","rentTotal":"76582.37","paymentType":"月付","period":"24 ","brandName":"冰冰糖糖","rentType":"固定租金","storeNo":"B1-192","rentFreePeriod":"3","floorNo":"-1","deductPercent":"","contractEndTime":"2018-09-09","commercialType":"餐饮","contractId":"SYQBZZ16260","square":"11"},{"propertyFeeTotal":"25079.599999999999","contractStartTime":"2016-09-10","rentTotal":"127083.4","paymentType":"月付","period":"24 ","brandName":"薇薇摄影","rentType":"固定租金","storeNo":"B1-223","rentFreePeriod":"3","floorNo":"-1","deductPercent":"","contractEndTime":"2018-09-09","commercialType":"配套","contractId":"SYQBZZ16276","square":"15.9"},{"propertyFeeTotal":"121316.84","contractStartTime":"2016-09-10","rentTotal":"415618.67","paymentType":"月付","period":"24 ","brandName":"达芙妮","rentType":"固定租金","storeNo":"B1-67,B1-68","rentFreePeriod":"3","floorNo":"-1","deductPercent":"","contractEndTime":"2018-09-09","commercialType":"配套","contractId":"SYQBZZ16278","square":"76"},{"propertyFeeTotal":"439185","contractStartTime":"2016-09-10","rentTotal":"3174234","paymentType":"月付","period":"60 ","brandName":"DBar","rentType":"固定租金","storeNo":"S4b-1F-005","rentFreePeriod":"3","floorNo":"1","deductPercent":"","contractEndTime":"2021-09-09","commercialType":"餐饮","contractId":"SYQBZZ16280","square":"292.79000000000002"},{"propertyFeeTotal":"1155840","contractStartTime":"2016-09-10","rentTotal":"7559193.5999999996","paymentType":"季付","period":"96 ","brandName":"避风塘","rentType":"两者取高","storeNo":"H2c-1F-006/007/009,H2c-2F-005/007","rentFreePeriod":"6","floorNo":"1,2","deductPercent":"","contractEndTime":"2024-09-09","commercialType":"餐饮","contractId":"SYQBZZ16284","square":"481.6"},{"propertyFeeTotal":"58407.51","contractStartTime":"2016-09-10","rentTotal":"357948","paymentType":"月付","period":"36 ","brandName":"魔法分子冰淇淋","rentType":"固定租金","storeNo":"S1-4F-007","rentFreePeriod":"0","floorNo":"4","deductPercent":"","contractEndTime":"2019-09-09","commercialType":"餐饮","contractId":"SYQBZZ16296","square":"24.45"},{"propertyFeeTotal":"20915.11","contractStartTime":"2016-09-10","rentTotal":"102406.2","paymentType":"月付","period":"24 ","brandName":"樱佐","rentType":"固定租金","storeNo":"B1-226","rentFreePeriod":"1","floorNo":"-1","deductPercent":"","contractEndTime":"2018-09-09","commercialType":"配套","contractId":"SYQBZZ16299","square":"13"},{"propertyFeeTotal":"12576","contractStartTime":"2016-09-10","rentTotal":"102720.07","paymentType":"月付","period":"24 ","brandName":"和绣堂","rentType":"固定租金","storeNo":"T4-9","rentFreePeriod":"3","floorNo":"1","deductPercent":"","contractEndTime":"2018-09-09","commercialType":"配套","contractId":"SYQBZZ16301","square":"20.96"},{"propertyFeeTotal":"598629.73","contractStartTime":"2016-09-10","rentTotal":"0","paymentType":"季付","period":"120 ","brandName":"星巴克","rentType":"提成租金","storeNo":"s4a-1F-003b","rentFreePeriod":"0","floorNo":"1","deductPercent":"10%","contractEndTime":"2026-09-09","commercialType":"餐饮","contractId":"SYQBZZ16302","square":"200.49"},{"propertyFeeTotal":"607183.19999999995","contractStartTime":"2016-09-10","rentTotal":"2072726.24","paymentType":"月付","period":"36 ","brandName":"橙爱玩国","rentType":"固定租金","storeNo":"S4b-3F-003,S4b-3F-005","rentFreePeriod":"3","floorNo":"3","deductPercent":"","contractEndTime":"2019-09-09","commercialType":"儿童","contractId":"SYQBZZ16312","square":"259.48"},{"propertyFeeTotal":"380109.6","contractStartTime":"2016-09-10","rentTotal":"1270741.05","paymentType":"季付","period":"36 ","brandName":"热气球","rentType":"固定租金","storeNo":"S1-4F-003,S1-4F-005a","rentFreePeriod":"3","floorNo":"4","deductPercent":"","contractEndTime":"2019-09-09","commercialType":"儿童","contractId":"SYQBZZ16354","square":"162.44"},{"propertyFeeTotal":"953520","contractStartTime":"2016-09-10","rentTotal":"5012336.8","paymentType":"月付","period":"60 ","brandName":"不一班教育","rentType":"固定租金","storeNo":"T4-210,T4-211,T4-212,T4-213,T4-214,T4-215,T4-216,T4-217,T4-218,T4-379,T4-381","rentFreePeriod":"5","floorNo":"1,2","deductPercent":"","contractEndTime":"2021-09-09","commercialType":"配套","contractId":"SYQBZZ16305","square":"794.6"},{"propertyFeeTotal":"645300","contractStartTime":"2016-09-10","rentTotal":"3392126.99","paymentType":"月付","period":"60 ","brandName":"象上小学生","rentType":"固定租金","storeNo":"T4-391,T4-393,T4-201,T4-202,T4-203,T4-204,T4-205,T4-206","rentFreePeriod":"5","floorNo":"1,2","deductPercent":"","contractEndTime":"2021-09-09","commercialType":"儿童","contractId":"SYQBZZ16310","square":"537.75"},{"propertyFeeTotal":"699585","contractStartTime":"2016-09-10","rentTotal":"4925078.3899999997","paymentType":"月付","period":"60 ","brandName":"吹牛啤","rentType":"固定租金","storeNo":"S3-1F-001g,S3-1F-001f,S3-2F-001b,S3-2F-002/005a","rentFreePeriod":"2","floorNo":"1,2","deductPercent":"","contractEndTime":"2021-09-09","commercialType":"餐饮","contractId":"SYQBZZ16303","square":"466.39"},{"propertyFeeTotal":"361815.95","contractStartTime":"2016-09-10","rentTotal":"1172906.24","paymentType":"月付","period":"36 ","brandName":"妈祖面","rentType":"固定租金","storeNo":"S1-2F-006/007","rentFreePeriod":"2","floorNo":"2","deductPercent":"","contractEndTime":"2019-09-09","commercialType":"餐饮","contractId":"SYQBZZ16304","square":"151.46"},{"propertyFeeTotal":"46911.15","contractStartTime":"2016-09-10","rentTotal":"215919","paymentType":"月付","period":"24 ","brandName":"南洋茶铺","rentType":"固定租金","storeNo":"B1-93","rentFreePeriod":"1","floorNo":"-1","deductPercent":"","contractEndTime":"2018-09-09","commercialType":"餐饮","contractId":"SYQBZZ16309","square":"29.7"},{"propertyFeeTotal":"521400","contractStartTime":"2016-09-10","rentTotal":"2169024","paymentType":"月付","period":"60 ","brandName":"海伦多兰","rentType":"固定租金","storeNo":"T4-1F-387,T4-1F-389,T4-2F-207,T4-2F-208,T4-2F-209","rentFreePeriod":"0","floorNo":"1,2","deductPercent":"","contractEndTime":"2021-09-09","commercialType":"配套","contractId":"SYQBZZ16321","square":"347.6"},{"propertyFeeTotal":"103862.85","contractStartTime":"2016-09-10","rentTotal":"339415.65","paymentType":"月付","period":"36 ","brandName":"继光香香鸡","rentType":"固定租金","storeNo":"B1-63","rentFreePeriod":"3","floorNo":"-1","deductPercent":"","contractEndTime":"2019-09-09","commercialType":"餐饮","contractId":"SYQBZZ16360","square":"44.1"},{"propertyFeeTotal":"2371668","contractStartTime":"2016-09-10","rentTotal":"4672794.08","paymentType":"月付","period":"60 ","brandName":"农家媳妇","rentType":"固定租金","storeNo":"S5-4F-001","rentFreePeriod":"4","floorNo":"4","deductPercent":"","contractEndTime":"2021-09-09","commercialType":"餐饮","contractId":"SYQBZZ16346","square":"608.12"},{"propertyFeeTotal":"735298.2","contractStartTime":"2016-09-10","rentTotal":"2383434.5499999998","paymentType":"季付","period":"36 ","brandName":"MTEE","rentType":"两者取高","storeNo":"S4a-1F-006,S4a-1F-007,S4a-1F-008","rentFreePeriod":"3","floorNo":"1","deductPercent":"","contractEndTime":"2019-09-09","commercialType":"服装","contractId":"SYQBZZ16343","square":"314.23"},{"propertyFeeTotal":"13836.15","contractStartTime":"2016-09-10","rentTotal":"82560","paymentType":"月付","period":"24 ","brandName":"果粉store","rentType":"固定租金","storeNo":"B1-218","rentFreePeriod":"0","floorNo":"-1","deductPercent":"","contractEndTime":"2018-09-09","commercialType":"配套","contractId":"SYQBZZ16344","square":"8.6"},{"propertyFeeTotal":"2058870","contractStartTime":"2017-02-27","rentTotal":"7880674.9000000004","paymentType":"季付","period":"60 ","brandName":"FLAIR","rentType":"固定租金","storeNo":"T6-2F-201,T6-2F-202,T6-2F-203,T6-2F-204,T6-2F-205,T6-2F-206,T6-2F-207,T6-2F-208,T6-2F-209,T6-2F-210,T6-2F-211,T6-2F-212,T6-2F-213,T6-2F-214,T6-2F-215","rentFreePeriod":"3","floorNo":"2","deductPercent":"","contractEndTime":"2022-02-26","commercialType":"餐饮","contractId":"SYQBZZ16358","square":"1372.58"},{"propertyFeeTotal":"103689","contractStartTime":"2016-09-10","rentTotal":"705776.46","paymentType":"月付","period":"36 ","brandName":"龙炎","rentType":"固定租金","storeNo":"T5-1F-003","rentFreePeriod":"3","floorNo":"1","deductPercent":"","contractEndTime":"2019-09-09","commercialType":"餐饮","contractId":"SYQBZZ16359","square":"115.21"},{"propertyFeeTotal":"306540","contractStartTime":"2016-09-10","rentTotal":"940187","paymentType":"月付","period":"36 ","brandName":"麻麻鲁","rentType":"固定租金","storeNo":"S1-1F-001","rentFreePeriod":"3","floorNo":"1","deductPercent":"","contractEndTime":"2019-09-09","commercialType":"餐饮","contractId":"SYQBZZ16362","square":"131"},{"propertyFeeTotal":"164892","contractStartTime":"2016-09-10","rentTotal":"316501.03000000003","paymentType":"月付","period":"24 ","brandName":"oppo","rentType":"固定租金","storeNo":"B1-49,B1-51,B1-53","rentFreePeriod":"1","floorNo":"-1","deductPercent":"","contractEndTime":"2018-09-09","commercialType":"配套","contractId":"SYQBZZ16372","square":"105.7"},{"propertyFeeTotal":"28959.39","contractStartTime":"2016-09-10","rentTotal":"132672","paymentType":"月付","period":"24 ","brandName":"克菲斯","rentType":"固定租金","storeNo":"B1-219","rentFreePeriod":"1","floorNo":"-1","deductPercent":"","contractEndTime":"2018-09-09","commercialType":"餐饮","contractId":"SYQBZZ16376","square":"18"},{"propertyFeeTotal":"49874.5","contractStartTime":"2016-09-10","rentTotal":"149947","paymentType":"月付","period":"24 ","brandName":"阿姨很芒","rentType":"固定租金","storeNo":"B1-201","rentFreePeriod":"1","floorNo":"-1","deductPercent":"","contractEndTime":"2018-09-09","commercialType":"餐饮","contractId":"SYQBZZ16375","square":"31"},{"propertyFeeTotal":"1035216","contractStartTime":"2016-09-10","rentTotal":"2655904.16","paymentType":"月付","period":"60 ","brandName":"大晒","rentType":"固定租金","storeNo":"S3-4F-003","rentFreePeriod":"4","floorNo":"4","deductPercent":"","contractEndTime":"2021-09-09","commercialType":"餐饮","contractId":"SYQBZZ16373","square":"265.44"},{"propertyFeeTotal":"94922.44","contractStartTime":"2016-09-10","rentTotal":"368160","paymentType":"月付","period":"24 ","brandName":"江博士","rentType":"固定租金","storeNo":"S2-3F-002-1","rentFreePeriod":"0","floorNo":"3","deductPercent":"","contractEndTime":"2018-09-09","commercialType":"儿童","contractId":"SYQBZZ16378","square":"59"},{"propertyFeeTotal":"97218","contractStartTime":"2016-09-10","rentTotal":"838667.28","paymentType":"月付","period":"36 ","brandName":"喜士多","rentType":"固定租金","storeNo":"T3-409,T3-411","rentFreePeriod":"2","floorNo":"1","deductPercent":"","contractEndTime":"2019-09-09","commercialType":"超市","contractId":"SYQBZZ16377","square":"108.02"},{"propertyFeeTotal":"65702","contractStartTime":"2016-09-10","rentTotal":"325696","paymentType":"月付","period":"24 ","brandName":"吉满杯","rentType":"固定租金","storeNo":"S4a-4F-001c","rentFreePeriod":"1","floorNo":"4","deductPercent":"","contractEndTime":"2018-09-09","commercialType":"餐饮","contractId":"SYQBZZ16381","square":"42"},{"propertyFeeTotal":"585135","contractStartTime":"2016-11-15","rentTotal":"4355744.9400000004","paymentType":"月付","period":"60 ","brandName":"逢甲小馆","rentType":"固定租金","storeNo":"H2b-1F-001/002,H2b-2F-001/002","rentFreePeriod":"4","floorNo":"1,2","deductPercent":"","contractEndTime":"2021-11-14","commercialType":"餐饮","contractId":"SYQBZZ16416","square":"390.09"},{"propertyFeeTotal":"96252","contractStartTime":"2016-09-10","rentTotal":"116798.1","paymentType":"月付","period":"24 ","brandName":"VICTOR","rentType":"固定租金","storeNo":"S2-1F-001b-1","rentFreePeriod":"3","floorNo":"1","deductPercent":"","contractEndTime":"2018-09-09","commercialType":"配套","contractId":"SYQBZZ16391","square":"61.7"},{"propertyFeeTotal":"111571.2","contractStartTime":"2016-09-10","rentTotal":"379421.55","paymentType":"月付","period":"36 ","brandName":"Carrera卡雷拉路轨赛车","rentType":"固定租金","storeNo":"S1-3F-008","rentFreePeriod":"3","floorNo":"3","deductPercent":"","contractEndTime":"2019-09-09","commercialType":"儿童","contractId":"SYQBZZ16406","square":"47.68"},{"propertyFeeTotal":"861315","contractStartTime":"2016-09-10","rentTotal":"2667868","paymentType":"月付","period":"60 ","brandName":"龙蒸虎豆","rentType":"固定租金","storeNo":"S1-1F-019a/020b","rentFreePeriod":"2","floorNo":"1","deductPercent":"","contractEndTime":"2021-09-09","commercialType":"餐饮","contractId":"SYQBZZ16407","square":"220.85"},{"propertyFeeTotal":"45240","contractStartTime":"2016-09-10","rentTotal":"162482.17000000001","paymentType":"月付","period":"24 ","brandName":"格格小物","rentType":"固定租金","storeNo":"B1-216","rentFreePeriod":"3","floorNo":"-1","deductPercent":"","contractEndTime":"2018-09-09","commercialType":"配套","contractId":"SYQBZZ16403","square":"29"},{"propertyFeeTotal":"313794","contractStartTime":"2016-09-10","rentTotal":"972225","paymentType":"月付","period":"36 ","brandName":"柯莹珠宝","rentType":"固定租金","storeNo":"B1-7/9-R","rentFreePeriod":"2","floorNo":"-1","deductPercent":"","contractEndTime":"2019-09-09","commercialType":"配套","contractId":"SYQBZZ16405","square":"134.1"},{"propertyFeeTotal":"111312","contractStartTime":"2016-10-01","rentTotal":"957777.92000000004","paymentType":"月付","period":"36 ","brandName":"四海游龙","rentType":"固定租金","storeNo":"T3-4,T3-6","rentFreePeriod":"1","floorNo":"1","deductPercent":"","contractEndTime":"2019-09-30","commercialType":"餐饮","contractId":"SYQBZZ16408","square":"123.68"},{"propertyFeeTotal":"48360","contractStartTime":"2016-09-10","rentTotal":"164227.67000000001","paymentType":"月付","period":"24 ","brandName":"玉品番达","rentType":"固定租金","storeNo":"B1-202","rentFreePeriod":"1","floorNo":"-1","deductPercent":"","contractEndTime":"2018-09-09","commercialType":"餐饮","contractId":"SYQBZZ16419","square":"31"},{"propertyFeeTotal":"302562","contractStartTime":"2016-09-24","rentTotal":"1160165.8","paymentType":"月付","period":"36 ","brandName":"金伯利珠宝","rentType":"固定租金","storeNo":"B1-15/17","rentFreePeriod":"3","floorNo":"-1","deductPercent":"","contractEndTime":"2019-09-23","commercialType":"配套","contractId":"SYQBZZ16417","square":"129.30000000000001"},{"propertyFeeTotal":"2268708","contractStartTime":"2016-10-25","rentTotal":"4529601.57","paymentType":"月付","period":"60 ","brandName":"热刺商店","rentType":"两者取高","storeNo":"S5-2F-001a","rentFreePeriod":"3","floorNo":"2","deductPercent":"","contractEndTime":"2021-10-24","commercialType":"配套","contractId":"SYQBZZ16425","square":"581.72"},{"propertyFeeTotal":"170970.35","contractStartTime":"2016-09-10","rentTotal":"618937.36","paymentType":"月付","period":"36 ","brandName":"嘉里奥","rentType":"固定租金","storeNo":"S3-1F-001a","rentFreePeriod":"3","floorNo":"1","deductPercent":"","contractEndTime":"2019-09-09","commercialType":"服装","contractId":"SYQBZZ16080","square":"71.569999999999993"},{"propertyFeeTotal":"26063.45","contractStartTime":"2016-09-10","rentTotal":"114696","paymentType":"月付","period":"24 ","brandName":"臻好时","rentType":"固定租金","storeNo":"S3-3F-002","rentFreePeriod":"0","floorNo":"3","deductPercent":"","contractEndTime":"2018-09-09","commercialType":"餐饮","contractId":"SYQBZZ16082","square":"16.2"}]